akita_django/__init__.py
akita_django/har.py
akita_django/middleware.py
akita_django/test.py
akita_django-0.1.1.dist-info/LICENSE
akita_django-0.1.1.dist-info/METADATA
akita_django-0.1.1.dist-info/WHEEL
akita_django-0.1.1.dist-info/top_level.txt
akita_django-0.1.1.dist-info/RECORD
