Metadata-Version: 2.1
Name: akita-django
Version: 0.1.1
Summary: Utilities for connecting Akita to Django
Home-page: https://github.com/akitasoftware/akita-django
Author: Cole Schlesinger
Author-email: cole@akitasoftware.com
Classifier: Programming Language :: Python :: 3
Classifier: License :: OSI Approved :: Apache Software License
Classifier: Operating System :: OS Independent
Requires-Python: >=3.6
License-File: LICENSE
Requires-Dist: akita-har
Requires-Dist: requests
Requires-Dist: django
